<StackLayout class="sidedrawer-left">
  <StackLayout class="sidedrawer-header-brand">
    <Label text=" " />
    <Label text="Navigation Menu" class="sidedrawer-header-brand"/>
  </StackLayout>
  <ScrollView>
    <StackLayout class="sidedrawer-content">
      <Button text="Scanner" class="btn btn-primary" tap="navigateToScanner" />
      <Button text="Arrows" class="btn btn-primary" tap="navigateToArrows" />
      <Button text="Accelerometer" class="btn btn-primary" tap="navigateToAccelerometer" />
      <Button text="Joystick" class="btn btn-primary" tap="navigateToJoystick" />
      <Button text="Sound" class="btn btn-primary" tap="navigateToSound" />
      <Button text="Lights" class="btn btn-primary" tap="navigateToLights" />
    </StackLayout>
  </ScrollView>
</StackLayout>